src/__init__.py
src/carboncopy/__init__.py
src/carboncopy/cli_utils.py
src/carboncopy/config_defaults.py
src/carboncopy/constants.py
src/carboncopy/fs_utils.py
src/carboncopy/git_utils.py
src/carboncopy/main.py
src/carboncopy/print_utils.py
src/carboncopy/use_cases.py
tests/__init__.py
tests/setup.py
tests/tasks.py
tests/test_use_cases.py
carboncopy-0.0.1.dist-info/LICENSE
carboncopy-0.0.1.dist-info/METADATA
carboncopy-0.0.1.dist-info/WHEEL
carboncopy-0.0.1.dist-info/entry_points.txt
carboncopy-0.0.1.dist-info/top_level.txt
carboncopy-0.0.1.dist-info/RECORD
