Metadata-Version: 2.1
Name: carboncopy
Version: 0.0.1
Summary: A small CLI utility to keep your repositories up-to-date with their templates
Home-page: https://pypi.org/project/carboncopy/
Author: Marc Cataford
Author-email: c.marcandre@gmail.com
License: MIT
Project-URL: Source, https://github.com/mcataford/carboncopy
Project-URL: Bug Reports, https://github.com/mcataford/carboncopy/issues
Platform: UNKNOWN
Classifier: Development Status :: 3 - Alpha
Classifier: Environment :: Console
Classifier: License :: OSI Approved :: MIT License
Classifier: Topic :: Software Development :: Version Control :: Git
Requires-Python: >=3.6
Requires-Dist: requests (>=2.22.0)
Requires-Dist: inquirer (==2.6.3)
